{
  "theme": {
    "--an-font-family": "'Overused Grotesk', 'SF Pro Display', system-ui, sans-serif",
    "--an-font-weight": "400",
    "--an-font-weight-medium": "500",
    "--an-font-weight-semibold": "600",
    "--an-text-size": "14px",
    "--an-text-size-sm": "13px",
    "--an-text-size-xs": "11px",
    "--an-line-height": "1.6",
    "--an-border-radius": "14px",
    "--an-message-border-radius": "14px",
    "--an-input-border-radius": "14px",
    "--an-tool-border-radius": "10px",
    "--an-code-border-radius": "8px",
    "--an-send-button-border-radius": "9999px",
    "--an-user-message-padding": "12px 16px",
    "--an-input-padding": "14px 18px",
    "--an-send-button-size": "32px",
    "--an-stop-button-size": "32px",
    "--an-max-width": "100%",
    "--an-message-style": "full-width",
    "--an-message-density": "relaxed",
    "--an-input-style": "bordered",
    "--an-send-button-style": "circle-icon",
    "--an-stop-button-style": "circle-square",
    "--an-thinking-display": "streaming",
    "--an-code-action-display": "diff-card",
    "--an-bash-display": "terminal-card",
    "--an-search-display": "rich-group",
    "--an-tool-call-style": "compact",
    "--an-text-contrast": "normal",
    "--an-attachment-button-style": "hidden",
    "--an-model-selector-position": "hidden",
    "--an-mode-selector-position": "hidden",
    "--an-show-tool-icons": "true",
    "--an-message-shadow": "false",
    "--an-show-copy-button": "true",
    "--an-show-window-chrome": "false",
    "--an-input-fill": "true",
    "--an-input-shadow-toggle": "false",
    "--an-input-placeholder": "Ask Minerva anything..."
  },
  "dark": {
    "--an-background": "transparent",
    "--an-background-secondary": "rgba(255,255,255,0.06)",
    "--an-background-tertiary": "rgba(255,255,255,0.03)",
    "--an-foreground": "rgba(255,255,255,0.92)",
    "--an-foreground-muted": "rgba(255,255,255,0.45)",
    "--an-foreground-subtle": "rgba(255,255,255,0.25)",
    "--an-border-color": "rgba(255,255,255,0.08)",
    "--an-border-color-light": "rgba(255,255,255,0.05)",
    "--an-primary-color": "rgba(255,255,255,0.7)",
    "--an-user-message-bg": "rgba(255,255,255,0.06)",
    "--an-user-message-text": "rgba(255,255,255,0.92)",
    "--an-input-background": "rgba(255,255,255,0.05)",
    "--an-input-border-color": "rgba(255,255,255,0.10)",
    "--an-input-color": "rgba(255,255,255,0.92)",
    "--an-input-placeholder-color": "rgba(255,255,255,0.25)",
    "--an-send-button-bg": "rgba(255,255,255,0.85)",
    "--an-send-button-color": "#0c0e1c",
    "--an-stop-button-bg": "rgba(255,255,255,0.85)",
    "--an-stop-button-color": "#0c0e1c",
    "--an-tool-background": "rgba(255,255,255,0.04)",
    "--an-tool-border-color": "rgba(255,255,255,0.08)",
    "--an-tool-color": "rgba(255,255,255,0.8)",
    "--an-tool-color-muted": "rgba(255,255,255,0.4)",
    "--an-code-background": "rgba(0,0,0,0.3)",
    "--an-code-color": "rgba(255,255,255,0.8)"
  },
  "light": {
    "--an-background": "transparent",
    "--an-background-secondary": "rgba(0,0,0,0.04)",
    "--an-background-tertiary": "rgba(0,0,0,0.02)",
    "--an-foreground": "rgba(0,0,0,0.88)",
    "--an-foreground-muted": "rgba(0,0,0,0.45)",
    "--an-foreground-subtle": "rgba(0,0,0,0.25)",
    "--an-border-color": "rgba(0,0,0,0.08)",
    "--an-border-color-light": "rgba(0,0,0,0.05)",
    "--an-primary-color": "rgba(0,0,0,0.7)",
    "--an-user-message-bg": "rgba(0,0,0,0.04)",
    "--an-user-message-text": "rgba(0,0,0,0.88)",
    "--an-input-background": "rgba(0,0,0,0.03)",
    "--an-input-border-color": "rgba(0,0,0,0.10)",
    "--an-input-color": "rgba(0,0,0,0.88)",
    "--an-input-placeholder-color": "rgba(0,0,0,0.25)",
    "--an-send-button-bg": "rgba(0,0,0,0.85)",
    "--an-send-button-color": "#ffffff",
    "--an-stop-button-bg": "rgba(0,0,0,0.85)",
    "--an-stop-button-color": "#ffffff",
    "--an-tool-background": "rgba(0,0,0,0.03)",
    "--an-tool-border-color": "rgba(0,0,0,0.08)",
    "--an-tool-color": "rgba(0,0,0,0.8)",
    "--an-tool-color-muted": "rgba(0,0,0,0.4)",
    "--an-code-background": "rgba(0,0,0,0.05)",
    "--an-code-color": "rgba(0,0,0,0.8)"
  }
}
